ldap_hooks/__init__.py
ldap_hooks/_version.py
ldap_hooks/hooks.py
ldap_hooks/ldap.py
ldap_hooks/utils.py
ldap_hooks-0.1.2.dist-info/licenses/LICENSE
tests/__init__.py
tests/conftest.py
tests/test_ldap_hooks.py
tests/util.py
ldap_hooks-0.1.2.dist-info/METADATA
ldap_hooks-0.1.2.dist-info/WHEEL
ldap_hooks-0.1.2.dist-info/top_level.txt
ldap_hooks-0.1.2.dist-info/RECORD
