Metadata-Version: 2.4
Name: ldap_hooks
Version: 0.1.2
Summary: A set of Jupyter Spawner pre_spawn_hooks for creating/retrieving LDAP DIT entries during spawn
Home-page: https://github.com/rasmunk/ldap_hooks
Author: Rasmus Munk
Author-email: munk1@live.dk
License: MIT
Project-URL: Source Code, https://github.com/rasmunk/ldap_hooks
Keywords: Web,JupyterHub,Spawner,Hook
Classifier: Intended Audience :: Developers
Classifier: Intended Audience :: System Administrators
Classifier: Intended Audience :: Science/Research
Classifier: Programming Language :: Python :: 3.9
Classifier: Programming Language :: Python :: 3.10
Classifier: Programming Language :: Python :: 3.11
Classifier: Programming Language :: Python :: 3.12
License-File: LICENSE
Requires-Dist: ldap3>=2.9.1
Requires-Dist: traitlets>=5.14.3
Requires-Dist: gen>=0.1
Requires-Dist: tornado>=6.4.1
Provides-Extra: test
Requires-Dist: requests==2.32.4; extra == "test"
Requires-Dist: docker==7.1.0; extra == "test"
Requires-Dist: docutils==0.21.2; extra == "test"
Requires-Dist: flake8==7.1.2; extra == "test"
Requires-Dist: autopep8==2.3.2; extra == "test"
Requires-Dist: gen==0.1; extra == "test"
Requires-Dist: pytest==7.4.4; extra == "test"
Provides-Extra: dev
Requires-Dist: black>=24.10.0; extra == "dev"
Requires-Dist: docutils>=0.21.2; extra == "dev"
Requires-Dist: flake8>=7.1.2; extra == "dev"
Dynamic: author
Dynamic: author-email
Dynamic: classifier
Dynamic: description
Dynamic: home-page
Dynamic: keywords
Dynamic: license
Dynamic: license-file
Dynamic: project-url
Dynamic: provides-extra
Dynamic: requires-dist
Dynamic: summary
